shamanld/__init__.py
shamanld/shaman.py
shamanld/tester.py
shamanld/trainer.py
shamanld/data/model.json.gz
shamanld-1.1.1.dist-info/METADATA
shamanld-1.1.1.dist-info/RECORD
shamanld-1.1.1.dist-info/WHEEL
shamanld-1.1.1.dist-info/entry_points.txt
shamanld-1.1.1.dist-info/top_level.txt
