Metadata-Version: 2.1
Name: shamanld
Version: 1.1.1
Summary: Programming Language Detector
Home-page: https://github.com/Prev/shaman
Author: Youngsoo Lee
Author-email: prevdev@gmail.com
License: MIT
Keywords: language-detector,language,detector
Platform: UNKNOWN
